setup.py
scoi_lab3_json_xml_serializer.egg-info/PKG-INFO
scoi_lab3_json_xml_serializer.egg-info/SOURCES.txt
scoi_lab3_json_xml_serializer.egg-info/dependency_links.txt
scoi_lab3_json_xml_serializer.egg-info/top_level.txt
serializers/__init__.py
serializers/factory.py
serializers/json/__init__.py
serializers/json/json_parser.py
serializers/json/json_serializer.py
serializers/source/__init__.py
serializers/source/constants.py
serializers/source/serializer.py
serializers/xml/__init__.py
serializers/xml/xml_constants.py
serializers/xml/xml_parser.py
serializers/xml/xml_serializer.py
tests/__init__.py
tests/serialization_tests.py
tests/test_variables.py