Metadata-Version: 2.1
Name: scoi-lab3-json-xml-serializer
Version: 0.1
Summary: package for python (de)serialization in .json and .xml
Home-page: https://github.com/DrVaroZ/SCoL_labs/tree/lab3
Author: Vadim Zhur
Author-email: vadim10zhur@gmail.com
License: UNKNOWN
Platform: UNKNOWN
Classifier: Intended Audience :: Developers
Classifier: Programming Language :: Python :: 3.10
Classifier: Operating System :: OS Independent
